[
  {
    "uid": "3167081651",
    "nickname": "forcode"
  },
  {
    "uid": "9742512811",
    "nickname": "丹书铁券"
  },
  {
    "uid": "9002812276",
    "nickname": "okokok333"
  },
  {
    "uid": "1645252804",
    "nickname": "牛得草"
  },
  {
    "uid": "5858056225",
    "nickname": "九三"
  },
  {
    "uid": "1767450337",
    "nickname": "没时间的王无理"
  },
  {
    "uid": "8102984655",
    "nickname": "jh786"
  },
  {
    "uid": "8396246662",
    "nickname": "GreedFear"
  },
  {
    "uid": "1538598451",
    "nickname": "万法归宗"
  },
  {
    "uid": "3777170109",
    "nickname": "厚济天下"
  },
  {
    "uid": "9813181917",
    "nickname": "Jacky_He"
  },
  {
    "uid": "2978349313",
    "nickname": "黑寡妇淼婪儿"
  },
  {
    "uid": "2129489320",
    "nickname": "Dean_丁丁"
  },
  {
    "uid": "1638377010",
    "nickname": "大隐无言"
  },
  {
    "uid": "2164183023",
    "nickname": "亿利达"
  },
  {
    "uid": "3563983644",
    "nickname": "Frankel"
  },
  {
    "uid": "5633311140",
    "nickname": "盒饭你别忧伤"
  },
  {
    "uid": "6902035625",
    "nickname": "中庸吴振兴"
  },
  {
    "uid": "8510627167",
    "nickname": "再见雪球"
  },
  {
    "uid": "9479439613",
    "nickname": "天多"
  },
  {
    "uid": "7466783427",
    "nickname": "卢山林"
  },
  {
    "uid": "7422261471",
    "nickname": "猪飘飘"
  },
  {
    "uid": "3007723535",
    "nickname": "茶壶商人"
  },
  {
    "uid": "4936181774",
    "nickname": "南迦巴瓦1999"
  },
  {
    "uid": "5547009444",
    "nickname": "陌尚阡"
  }
]
